README.rst
setup.cfg
setup.py
key_value_db/__init__.py
key_value_db/key_value_db.py
key_value_db/key_value_object.py
key_value_db.egg-info/PKG-INFO
key_value_db.egg-info/SOURCES.txt
key_value_db.egg-info/dependency_links.txt
key_value_db.egg-info/not-zip-safe
key_value_db.egg-info/top_level.txt