Metadata-Version: 1.1
Name: key-value-db
Version: 1.1.7
Summary: Light weight package to quickly and easily manage, load, update and save key-value type database
Home-page: https://keyvaluedb.github.io/
Author: Adewale Azeez
Author-email: azeezadewale98@gmail.com
License: MIT
Keywords: key-value,database,python,package,quick,simple,dictionary
Platform: any
Classifier: Development Status :: 5 - Production/Stable
Classifier: Natural Language :: English
Classifier: License :: OSI Approved :: GNU Lesser General Public License v3 (LGPLv3)
Classifier: Topic :: Database
Classifier: Topic :: Database :: Database Engines/Servers
Classifier: Topic :: Database :: Front-Ends
Classifier: Programming Language :: Python
Classifier: Programming Language :: Python :: 2.7
Classifier: Programming Language :: Python :: 3
Classifier: Programming Language :: Python :: 3.4
Classifier: Programming Language :: Python :: 3.5
Classifier: Programming Language :: Python :: 3.6
Classifier: Programming Language :: Python :: 3.7
